<?xml version="1.0" encoding="utf-8"?>
<sketch id="7ddeebc7-92f4-4c99-b306-4928f06230b3">
  <point x="962" y="2275" pressure="127" time="1159077688130" name="point" id="ecb6dfda-8bec-4830-b000-ed4e7b90c22c" />
  <point x="961" y="2301" pressure="127" time="1159077688138" name="point" id="04201c5d-df2b-4057-9665-27c3feecd9a0" />
  <point x="959" y="2326" pressure="127" time="1159077688145" name="point" id="49c49839-6681-46dd-9eab-e38b15fd125e" />
  <point x="970" y="2450" pressure="127" time="1159077688250" name="point" id="2d1f830f-98c2-4eab-9efd-f6807b91b199" />
  <point x="978" y="2452" pressure="127" time="1159077688258" name="point" id="8e8fd96a-46f2-44ef-8fdf-ca7a96abc41a" />
  <point x="984" y="2452" pressure="127" time="1159077688266" name="point" id="25c33b8e-401c-4a11-ba05-30ea7c10572c" />
  <point x="994" y="2453" pressure="127" time="1159077688273" name="point" id="812571c0-35ed-4ae8-90b6-630988dc9a07" />
  <point x="1006" y="2454" pressure="127" time="1159077688281" name="point" id="3516794d-2baf-4904-984c-369a247eeb0f" />
  <point x="1019" y="2451" pressure="127" time="1159077688288" name="point" id="03e111d7-ebdc-4264-94b9-a48fd9c4ac8b" />
  <point x="1033" y="2450" pressure="127" time="1159077688296" name="point" id="845b0ea3-129d-41ee-a149-ffeb3f8a2b7a" />
  <point x="1049" y="2449" pressure="127" time="1159077688303" name="point" id="add59f46-c85c-4fef-a4e0-846b2073fb2a" />
  <point x="1067" y="2447" pressure="127" time="1159077688311" name="point" id="347561da-9305-4a48-9eb9-c1bf6ba1948c" />
  <point x="1084" y="2445" pressure="127" time="1159077688318" name="point" id="c9277060-3993-4712-bb8d-85bf34fa6cbb" />
  <point x="1102" y="2444" pressure="127" time="1159077688326" name="point" id="5e2869bf-32f1-45e7-ac0d-7b5c90b6fa73" />
  <point x="1118" y="2441" pressure="127" time="1159077688333" name="point" id="4379f750-0722-4af8-bcb8-099405933d7f" />
  <point x="1131" y="2439" pressure="127" time="1159077688341" name="point" id="09603157-eef0-4a14-a78c-e5cf0733197b" />
  <point x="1144" y="2440" pressure="127" time="1159077688348" name="point" id="d7bcfaae-0961-4ac4-a918-4b06b0902822" />
  <point x="1154" y="2440" pressure="127" time="1159077688356" name="point" id="cb949513-bbcf-4b9b-a40b-f9e5ea2dd474" />
  <point x="1162" y="2440" pressure="127" time="1159077688363" name="point" id="ff830d68-64da-4d6a-8ba8-59ac878a273e" />
  <point x="1162" y="2440" pressure="127" time="1159077688371" name="point" id="20427a76-da10-4745-a69e-152f5562b88f" />
  <point x="1170" y="2440" pressure="127" time="1159077688378" name="point" id="a4454a23-2b2b-43b0-a0c8-91194ea2f394" />
  <point x="1170" y="2440" pressure="127" time="1159077688386" name="point" id="0e88aabe-1917-46af-876d-a3d12132c949" />
  <point x="1170" y="2440" pressure="127" time="1159077688393" name="point" id="694380aa-ee9e-4667-8015-78bd6ee66f4d" />
  <point x="1170" y="2440" pressure="127" time="1159077688401" name="point" id="ac3ce4f8-4583-47ee-b9e6-95efb1fdd8ab" />
  <point x="1170" y="2440" pressure="127" time="1159077688408" name="point" id="d2e5fff6-41d7-43b1-a75e-26fc1be1a07b" />
  <point x="1170" y="2440" pressure="127" time="1159077688416" name="point" id="9d939cf3-bb8e-4de4-a687-f564ace6e9c8" />
  <point x="1166" y="2433" pressure="127" time="1159077688423" name="point" id="9f36e510-7883-4cf4-8716-d2b6e705eb17" />
  <point x="1166" y="2433" pressure="127" time="1159077688431" name="point" id="0c915a44-d801-43fd-96ab-40137d37871a" />
  <point x="1166" y="2433" pressure="127" time="1159077688438" name="point" id="bc1f20d8-2196-4dff-87a6-d7088dce9d69" />
  <point x="1166" y="2433" pressure="127" time="1159077688446" name="point" id="50c8bd8a-577f-4385-8223-97790a049a28" />
  <point x="1179" y="2306" pressure="127" time="1159077688609" name="point" id="0bfe11a0-9c55-4d75-8951-45878c1cb4eb" />
  <point x="1179" y="2306" pressure="127" time="1159077688616" name="point" id="3cb105e3-8ccb-41a2-893b-78005f24324a" />
  <point x="1172" y="2308" pressure="127" time="1159077688624" name="point" id="115b005b-1f89-4ad4-9bae-a8d97acb65c2" />
  <point x="1172" y="2308" pressure="127" time="1159077688631" name="point" id="ca86bfbe-dae5-4193-8422-923aac84d653" />
  <point x="1171" y="2320" pressure="127" time="1159077688639" name="point" id="e22a6226-0cda-435a-b09e-b8d5cbb03b4c" />
  <point x="1169" y="2335" pressure="127" time="1159077688646" name="point" id="b21e30bb-3659-4a88-a935-5beaa4830c7b" />
  <point x="1169" y="2352" pressure="127" time="1159077688654" name="point" id="087b1a99-dab0-4138-85fe-e442e1212999" />
  <point x="1167" y="2373" pressure="127" time="1159077688661" name="point" id="4cf44815-74bd-40ac-b56e-4b15e3c8bb48" />
  <point x="1167" y="2396" pressure="127" time="1159077688669" name="point" id="3ab048e2-8185-4b41-98c6-ea3e2748c9ff" />
  <point x="1166" y="2424" pressure="127" time="1159077688676" name="point" id="ef88bf6e-3708-4f2d-8211-1e44d0fbac04" />
  <point x="1165" y="2451" pressure="127" time="1159077688684" name="point" id="8e3a442d-33e8-4bb3-bda1-025df6668b0f" />
  <point x="1164" y="2480" pressure="127" time="1159077688691" name="point" id="783415c9-a7c8-4706-b3b6-1a5fb275e0dd" />
  <point x="1163" y="2507" pressure="127" time="1159077688699" name="point" id="9d1e2411-8795-4e7a-a12d-2b74cffabac4" />
  <point x="1163" y="2531" pressure="127" time="1159077688706" name="point" id="2af04767-db3b-4b16-a0c9-2af54648521c" />
  <point x="1163" y="2550" pressure="127" time="1159077688714" name="point" id="5077f446-2c91-4545-8471-a1f5380bcacf" />
  <point x="1163" y="2565" pressure="127" time="1159077688721" name="point" id="0286e1e4-624f-42b6-86c0-c5c1e33ad90b" />
  <point x="1163" y="2579" pressure="127" time="1159077688729" name="point" id="397d2db4-cd85-4e1b-8af1-0a8da155b944" />
  <point x="1163" y="2579" pressure="127" time="1159077688736" name="point" id="ea5a56df-7bd4-4b77-89f7-452ba0a866e8" />
  <point x="1168" y="2590" pressure="127" time="1159077688744" name="point" id="d5856520-3c69-40b0-a768-3f8c241c2587" />
  <point x="1168" y="2590" pressure="127" time="1159077688751" name="point" id="1b0fd933-4912-47a3-bae6-021399a5d62a" />
  <point x="1177" y="2582" pressure="127" time="1159077688759" name="point" id="ea2021e4-d80d-4d6d-94f5-0f6dae3fec90" />
  <point x="1177" y="2582" pressure="127" time="1159077688766" name="point" id="f6aae065-3a46-49b5-969a-573c845688c2" />
  <point x="1186" y="2562" pressure="127" time="1159077688774" name="point" id="f34b7353-4ba7-4afd-bc18-8aaf42a2db15" />
  <point x="1188" y="2552" pressure="127" time="1159077688781" name="point" id="685d93e3-b0ea-48b0-864d-aca25699d750" />
  <point x="1194" y="2532" pressure="127" time="1159077688789" name="point" id="728a8aaf-101d-405d-bd30-adfcecee332f" />
  <point x="1161" y="2309" pressure="127" time="1159077688982" name="point" id="dc417fa7-24c6-4840-8a06-d3a8ee0b58be" />
  <point x="1157" y="2316" pressure="127" time="1159077688989" name="point" id="ee858a9e-7244-45e5-a415-216123baa24a" />
  <point x="1157" y="2316" pressure="127" time="1159077688997" name="point" id="b68c6729-ee03-4831-8151-66fd671c12f1" />
  <point x="1161" y="2325" pressure="127" time="1159077689004" name="point" id="e3d4e053-0430-4237-aad7-f9ab6e12008d" />
  <point x="1165" y="2332" pressure="127" time="1159077689012" name="point" id="b4b55fd7-7e62-45ce-89c1-836504e3f9ac" />
  <point x="1174" y="2336" pressure="127" time="1159077689019" name="point" id="9ed982d9-b88d-4655-b618-6c5597df5a5c" />
  <point x="1182" y="2341" pressure="127" time="1159077689027" name="point" id="a25a8e32-d14f-4a46-8bc8-cefb17f36cd8" />
  <point x="1195" y="2345" pressure="127" time="1159077689034" name="point" id="5225d6fb-56b8-42af-8944-e8d80fcf3d67" />
  <point x="1210" y="2350" pressure="127" time="1159077689042" name="point" id="69b0851c-1b5f-4fb7-b054-e4cffae9a001" />
  <point x="1226" y="2356" pressure="127" time="1159077689049" name="point" id="9006b223-02af-40a9-bef7-2bc4c67a826d" />
  <point x="1243" y="2364" pressure="127" time="1159077689057" name="point" id="993fa773-4494-4c92-b69e-44b9b4a9f8f5" />
  <point x="1261" y="2370" pressure="127" time="1159077689064" name="point" id="45b5b92c-2da3-4318-bf37-70e8264fb62e" />
  <point x="1278" y="2377" pressure="127" time="1159077689072" name="point" id="7ee4a99f-9e98-408a-8a4a-83172aa30ef6" />
  <point x="1294" y="2385" pressure="127" time="1159077689079" name="point" id="739256c7-fd5c-459b-9f47-6b5044a3efe7" />
  <point x="1308" y="2393" pressure="127" time="1159077689087" name="point" id="253270fe-4f23-4a9f-a462-098a7f5c6792" />
  <point x="1323" y="2401" pressure="127" time="1159077689094" name="point" id="c9c777b6-cdb9-4c74-9444-9e66b66d4f4b" />
  <point x="1332" y="2410" pressure="127" time="1159077689102" name="point" id="15eac86c-1cb0-4563-a2b5-10ab9d68a168" />
  <point x="1340" y="2417" pressure="127" time="1159077689109" name="point" id="e06d8e41-b4b2-456b-99e6-79434f344339" />
  <point x="1340" y="2417" pressure="127" time="1159077689117" name="point" id="de98c2ea-1ce3-402f-bc82-4356e8b92717" />
  <point x="1348" y="2431" pressure="127" time="1159077689125" name="point" id="60ea9a07-4e29-4ad4-a3e7-0b6b66f1bda2" />
  <point x="1348" y="2440" pressure="127" time="1159077689132" name="point" id="80aa12bf-461d-4d78-8a0d-d0baca46daa5" />
  <point x="1346" y="2447" pressure="127" time="1159077689140" name="point" id="4d07472d-030b-47cb-a994-9af3054b99e1" />
  <point x="1342" y="2457" pressure="127" time="1159077689147" name="point" id="c13e3fe2-54ec-45a2-95da-b51df8e2bc37" />
  <point x="1335" y="2467" pressure="127" time="1159077689155" name="point" id="07894d9b-bd13-4d94-aa57-bbf6a71293b4" />
  <point x="1327" y="2477" pressure="127" time="1159077689162" name="point" id="7f773466-d9b6-45a6-9dc6-6c889ef79129" />
  <point x="1314" y="2489" pressure="127" time="1159077689170" name="point" id="c65bd5cf-f9ae-432d-8521-da5fa8025623" />
  <point x="1299" y="2501" pressure="127" time="1159077689177" name="point" id="857162d7-5aba-483f-813f-e1f4e9c7d22f" />
  <point x="1284" y="2513" pressure="127" time="1159077689185" name="point" id="ce93b200-ff4c-4713-877a-bebb0b916e8f" />
  <point x="1267" y="2525" pressure="127" time="1159077689192" name="point" id="a8e28994-c218-4e18-8f26-c1b77bba444e" />
  <point x="1251" y="2537" pressure="127" time="1159077689200" name="point" id="df6c0b76-8730-4780-a6d7-8fc9341cb806" />
  <point x="1237" y="2546" pressure="127" time="1159077689207" name="point" id="b5d6d8e2-a29e-414e-b9a1-8a9f09cab310" />
  <point x="1223" y="2555" pressure="127" time="1159077689215" name="point" id="d4c69997-62e9-4664-9327-c3696e2a2fd8" />
  <point x="1210" y="2563" pressure="127" time="1159077689222" name="point" id="23429e2f-3ee0-4060-b98d-7ac04644a874" />
  <point x="1203" y="2571" pressure="127" time="1159077689230" name="point" id="118ed935-d6b6-4ae4-927b-107e34d1de21" />
  <point x="1203" y="2571" pressure="127" time="1159077689237" name="point" id="239260ab-1bf1-4045-b88b-335834e74268" />
  <point x="1194" y="2581" pressure="127" time="1159077689245" name="point" id="805b0db3-cb07-48bb-a200-63ba8cd40f78" />
  <point x="1194" y="2581" pressure="127" time="1159077689252" name="point" id="8a9f5598-fb04-4f5c-8b2a-345251a36d43" />
  <point x="1194" y="2581" pressure="127" time="1159077689260" name="point" id="01e17911-7fed-420a-808f-c4e0da6a8730" />
  <point x="1194" y="2581" pressure="127" time="1159077689267" name="point" id="83ff177f-7f73-45c9-91e7-fbcf7f456e6f" />
  <point x="1204" y="2582" pressure="127" time="1159077689275" name="point" id="47861bea-a30e-4e60-8bd3-0d065469f833" />
  <point x="1204" y="2582" pressure="127" time="1159077689282" name="point" id="7892c6e6-0c06-457e-9ce7-1e10bfe04e60" />
  <point x="1220" y="2570" pressure="127" time="1159077689290" name="point" id="cd557fbc-9dff-4c16-a0c1-84addc4c4db5" />
  <point x="1229" y="2565" pressure="127" time="1159077689297" name="point" id="ae5291b6-e1fe-44d8-84f0-3dbf8864e2c4" />
  <point x="1242" y="2554" pressure="127" time="1159077689305" name="point" id="bd5f6879-c368-4365-a128-a3a4600c1e55" />
  <point x="1466" y="2396" pressure="127" time="1159077689504" name="point" id="ebd7cd86-1242-440d-99ce-641f779ff2fb" />
  <point x="1459" y="2394" pressure="127" time="1159077689512" name="point" id="d09d71d2-498d-4c9e-b411-ee57a64558ed" />
  <point x="1459" y="2394" pressure="127" time="1159077689519" name="point" id="8cab5fa6-0389-45ed-9835-f5a94632cf64" />
  <point x="1449" y="2390" pressure="127" time="1159077689527" name="point" id="4ad82693-52aa-4964-bc04-bf3e8b9d1fa8" />
  <point x="1442" y="2390" pressure="127" time="1159077689534" name="point" id="a741cced-f5f2-4542-9785-ab6cf5bb0637" />
  <point x="1435" y="2391" pressure="127" time="1159077689542" name="point" id="5208b7fe-c868-4d9a-8097-c5ad6b33ec03" />
  <point x="1423" y="2399" pressure="127" time="1159077689549" name="point" id="ee735eb3-b41a-4572-a6a5-feede83c0ae1" />
  <point x="1416" y="2403" pressure="127" time="1159077689557" name="point" id="876f2869-4af6-462e-ae90-7868912e1eb7" />
  <point x="1404" y="2415" pressure="127" time="1159077689564" name="point" id="09822aee-6d43-4cbe-be25-c8714278326a" />
  <point x="1398" y="2424" pressure="127" time="1159077689572" name="point" id="1b8cc9c7-43f0-4071-962e-4501081df030" />
  <point x="1391" y="2436" pressure="127" time="1159077689579" name="point" id="a1a2a187-67b6-49b8-a0db-73568cd59886" />
  <point x="1385" y="2445" pressure="127" time="1159077689587" name="point" id="bbfa77d6-62a3-4203-a78b-570b94247e58" />
  <point x="1381" y="2456" pressure="127" time="1159077689594" name="point" id="f7ffba9c-c87a-4f51-8d22-c76d381156da" />
  <point x="1381" y="2463" pressure="127" time="1159077689602" name="point" id="892c164c-2a5a-4dbf-9275-41ebf77835d0" />
  <point x="1383" y="2471" pressure="127" time="1159077689609" name="point" id="220e8dd2-08d4-4180-b338-4f38ca180dce" />
  <point x="1383" y="2471" pressure="127" time="1159077689617" name="point" id="9e4d0b3e-60ba-4d88-905c-61972a764695" />
  <point x="1398" y="2481" pressure="127" time="1159077689625" name="point" id="7530025e-1f8f-4380-a0fd-c52144500ab2" />
  <point x="1408" y="2485" pressure="127" time="1159077689632" name="point" id="49f2012e-1884-4a63-b88b-486b1b111ccf" />
  <point x="1421" y="2487" pressure="127" time="1159077689640" name="point" id="c36580eb-0487-48da-9080-9b8820002df2" />
  <point x="1438" y="2489" pressure="127" time="1159077689647" name="point" id="20cedf2d-2062-499a-b698-ab45f9be4364" />
  <point x="1457" y="2488" pressure="127" time="1159077689655" name="point" id="8541b8c8-a5f5-46a8-9a47-fab918ed0497" />
  <point x="1473" y="2487" pressure="127" time="1159077689662" name="point" id="861b484a-b4f5-4d92-9419-a0022a73cbbf" />
  <point x="1490" y="2485" pressure="127" time="1159077689670" name="point" id="5093ecac-2865-44fe-b797-a3239956049b" />
  <point x="1504" y="2481" pressure="127" time="1159077689677" name="point" id="e5d18563-c6b7-49a0-92b1-513ac3fc1d3b" />
  <point x="1517" y="2475" pressure="127" time="1159077689685" name="point" id="3d007996-b393-49b0-9e04-8bc4e9ad4fa3" />
  <point x="1528" y="2467" pressure="127" time="1159077689692" name="point" id="a5d51877-551c-4fa6-b7dd-78793ff321f8" />
  <point x="1536" y="2458" pressure="127" time="1159077689700" name="point" id="84c9bd56-601c-43a3-be41-38699fb3af9f" />
  <point x="1539" y="2450" pressure="127" time="1159077689707" name="point" id="52bf3292-e6b9-4b2e-895a-f5db446c98cd" />
  <point x="1536" y="2442" pressure="127" time="1159077689715" name="point" id="21d9066d-452d-42d9-93d6-e192ec837ad9" />
  <point x="1533" y="2432" pressure="127" time="1159077689722" name="point" id="991ea037-e366-4bbd-8dc9-88b70d6f392d" />
  <point x="1526" y="2423" pressure="127" time="1159077689730" name="point" id="9084f6be-53c7-4375-be87-1e1d68ccdc24" />
  <point x="1516" y="2415" pressure="127" time="1159077689737" name="point" id="e9765217-41d9-4111-be1b-a78332940e4f" />
  <point x="1506" y="2406" pressure="127" time="1159077689745" name="point" id="e6828dc9-9bf5-4456-a6cc-fa7373f48ad1" />
  <point x="1494" y="2400" pressure="127" time="1159077689752" name="point" id="92fc3c59-f2dd-4fc3-914b-fa59202ab190" />
  <point x="1485" y="2393" pressure="127" time="1159077689760" name="point" id="c7525e84-07b7-4579-b8a4-94478874d2b9" />
  <point x="1474" y="2390" pressure="127" time="1159077689767" name="point" id="e3e49762-494e-4151-934b-86e844428fd1" />
  <point x="1467" y="2383" pressure="127" time="1159077689775" name="point" id="5425b762-d5e5-490a-9f41-f57b7bb88756" />
  <point x="1467" y="2383" pressure="127" time="1159077689782" name="point" id="edc2ecdf-1df9-47d9-b32c-cb27b5ee8d44" />
  <point x="1460" y="2382" pressure="127" time="1159077689790" name="point" id="244c4cfa-0508-4a27-b621-48450ee2eab8" />
  <point x="1460" y="2382" pressure="127" time="1159077689797" name="point" id="f26d107d-671a-423b-a2ab-2b5355840140" />
  <point x="1460" y="2382" pressure="127" time="1159077689805" name="point" id="65be1789-4618-4e75-bc95-a20354c08ffe" />
  <point x="1558" y="2441" pressure="127" time="1159077727818" name="point" id="c3b265e1-3b0e-40e4-816a-f7978406ca2f" />
  <point x="1549" y="2446" pressure="127" time="1159077727826" name="point" id="7abd8006-dd6b-4682-b193-7b43d2de0b28" />
  <point x="1549" y="2446" pressure="127" time="1159077727833" name="point" id="ddb236b1-85b4-4eff-ba9f-165c51b98f57" />
  <point x="1549" y="2446" pressure="127" time="1159077727841" name="point" id="04afb804-fffb-41ca-8ff7-421237356396" />
  <point x="1549" y="2446" pressure="127" time="1159077727848" name="point" id="fc8bb604-d879-4743-9eb4-826dbea37fa5" />
  <point x="1549" y="2446" pressure="127" time="1159077727856" name="point" id="ea900bb7-2bd0-4a5c-8874-dc4de6c7a50f" />
  <point x="1549" y="2446" pressure="127" time="1159077727863" name="point" id="388400ef-6c17-45d2-b025-f713b29aabd5" />
  <point x="1549" y="2446" pressure="127" time="1159077727871" name="point" id="c1889ada-f2c0-457a-bfb9-58b0e6b23a89" />
  <point x="1549" y="2446" pressure="127" time="1159077727878" name="point" id="ed0351d7-772e-49c0-ae16-128670f61cbf" />
  <point x="1549" y="2446" pressure="127" time="1159077727886" name="point" id="8aff1936-f232-469c-9f5a-0f8299ab8e42" />
  <point x="1549" y="2446" pressure="127" time="1159077727893" name="point" id="da49360e-e469-4d13-979f-c89578f9969f" />
  <point x="1549" y="2446" pressure="127" time="1159077727901" name="point" id="3f34fea7-a405-48df-8780-20d51928b00f" />
  <point x="1549" y="2446" pressure="127" time="1159077727908" name="point" id="757db3c2-cb0c-4b3e-8cd9-4afba3239cd6" />
  <point x="1549" y="2446" pressure="127" time="1159077727916" name="point" id="0879b83e-8098-413f-bbc0-7ac301e2c432" />
  <point x="1549" y="2446" pressure="127" time="1159077727923" name="point" id="533a4f0b-cfdc-4ec4-9798-8779cf2f0357" />
  <point x="1549" y="2446" pressure="127" time="1159077727931" name="point" id="ea2bced0-0dd1-4268-b821-c08201a9a365" />
  <point x="1549" y="2446" pressure="127" time="1159077727938" name="point" id="50778b09-5991-42bf-8d73-fdc9c768fb2c" />
  <point x="1549" y="2446" pressure="127" time="1159077727946" name="point" id="a0c77fa0-c827-4294-bda4-60b90c582378" />
  <point x="1549" y="2446" pressure="127" time="1159077727953" name="point" id="0665b773-0d24-49ca-befa-4e49152e81f5" />
  <point x="1549" y="2446" pressure="127" time="1159077727961" name="point" id="42527744-e527-427a-9945-62640f07560a" />
  <point x="1549" y="2446" pressure="127" time="1159077727969" name="point" id="aa4aa014-23e2-4a10-b506-b04ce3b3e2d1" />
  <point x="1558" y="2443" pressure="127" time="1159077727976" name="point" id="d0d7303f-0a9c-4094-9d2c-8a0fd83f3050" />
  <point x="1558" y="2443" pressure="127" time="1159077727984" name="point" id="8f04be38-4eff-4316-bd7e-7882716cee8b" />
  <point x="1567" y="2439" pressure="127" time="1159077727991" name="point" id="af298423-1935-4284-9c7f-ca1284767cd8" />
  <point x="1567" y="2439" pressure="127" time="1159077727999" name="point" id="7c847f39-e505-4d54-b468-de5c138d4e8b" />
  <point x="1580" y="2435" pressure="127" time="1159077728006" name="point" id="eb032651-25f5-44fb-ae7f-be9ba1cc8841" />
  <point x="1580" y="2435" pressure="127" time="1159077728014" name="point" id="424f699e-7348-4889-b31c-87f16696d1e4" />
  <point x="1593" y="2432" pressure="127" time="1159077728021" name="point" id="8239dace-c0fd-4e4e-a95e-43af38c2566f" />
  <point x="1601" y="2430" pressure="127" time="1159077728029" name="point" id="5793130b-b58b-4009-a049-28aef309a681" />
  <point x="1610" y="2429" pressure="127" time="1159077728036" name="point" id="68137477-52a7-4f94-b711-5ed35042314e" />
  <point x="1619" y="2427" pressure="127" time="1159077728044" name="point" id="f051ab61-da84-478f-aaa2-c529bdf75fa1" />
  <point x="1628" y="2428" pressure="127" time="1159077728051" name="point" id="1b372e5c-88a3-492a-b552-23962300ecd0" />
  <point x="1636" y="2429" pressure="127" time="1159077728059" name="point" id="fad7cba8-dfcc-497f-b2e7-95b85ba48a3c" />
  <point x="1646" y="2428" pressure="127" time="1159077728066" name="point" id="17852771-29d7-4c66-b463-9399ce2cbeb8" />
  <point x="1656" y="2427" pressure="127" time="1159077728074" name="point" id="966fb974-71af-40c4-bb04-eb957c5549a4" />
  <point x="1666" y="2426" pressure="127" time="1159077728081" name="point" id="44924b11-7d4c-456b-a4d0-1c0cb05261f8" />
  <point x="1676" y="2425" pressure="127" time="1159077728089" name="point" id="c9cd9ab5-bcec-4a5a-8c2f-b593087a5b0f" />
  <point x="1686" y="2423" pressure="127" time="1159077728096" name="point" id="c43b9656-5c50-4f97-9510-97fcb79396f1" />
  <point x="1699" y="2424" pressure="127" time="1159077728104" name="point" id="2dc65c6e-e1ba-447c-a8cd-4211c8bcd99c" />
  <point x="1712" y="2422" pressure="127" time="1159077728111" name="point" id="9003fec7-6a59-489f-8dca-ffff5d9040b6" />
  <point x="1726" y="2420" pressure="127" time="1159077728119" name="point" id="3053208f-1880-4140-81a1-d2e6aae2726d" />
  <shape type="substroke" name="substroke" id="ad4753b6-5d94-4729-aea0-5218db55c355" time="1159077688453" x="951" y="2069" color="-16777216" height="385" width="219" penTip="Ball" penWidth="10" penHeight="10" raster="CopyPen" start="1e0fbf0e-56ec-46eb-a7de-6d6171cc8abe" end="50c8bd8a-577f-4385-8223-97790a049a28" source="ConverterJnt">
    <arg type="point">ecb6dfda-8bec-4830-b000-ed4e7b90c22c</arg>
    <arg type="point">04201c5d-df2b-4057-9665-27c3feecd9a0</arg>
    <arg type="point">49c49839-6681-46dd-9eab-e38b15fd125e</arg>
    <arg type="point">2d1f830f-98c2-4eab-9efd-f6807b91b199</arg>
    <arg type="point">8e8fd96a-46f2-44ef-8fdf-ca7a96abc41a</arg>
    <arg type="point">25c33b8e-401c-4a11-ba05-30ea7c10572c</arg>
    <arg type="point">812571c0-35ed-4ae8-90b6-630988dc9a07</arg>
    <arg type="point">3516794d-2baf-4904-984c-369a247eeb0f</arg>
    <arg type="point">03e111d7-ebdc-4264-94b9-a48fd9c4ac8b</arg>
    <arg type="point">845b0ea3-129d-41ee-a149-ffeb3f8a2b7a</arg>
    <arg type="point">add59f46-c85c-4fef-a4e0-846b2073fb2a</arg>
    <arg type="point">347561da-9305-4a48-9eb9-c1bf6ba1948c</arg>
    <arg type="point">c9277060-3993-4712-bb8d-85bf34fa6cbb</arg>
    <arg type="point">5e2869bf-32f1-45e7-ac0d-7b5c90b6fa73</arg>
    <arg type="point">4379f750-0722-4af8-bcb8-099405933d7f</arg>
    <arg type="point">09603157-eef0-4a14-a78c-e5cf0733197b</arg>
    <arg type="point">d7bcfaae-0961-4ac4-a918-4b06b0902822</arg>
    <arg type="point">cb949513-bbcf-4b9b-a40b-f9e5ea2dd474</arg>
    <arg type="point">ff830d68-64da-4d6a-8ba8-59ac878a273e</arg>
    <arg type="point">20427a76-da10-4745-a69e-152f5562b88f</arg>
    <arg type="point">a4454a23-2b2b-43b0-a0c8-91194ea2f394</arg>
    <arg type="point">0e88aabe-1917-46af-876d-a3d12132c949</arg>
    <arg type="point">694380aa-ee9e-4667-8015-78bd6ee66f4d</arg>
    <arg type="point">ac3ce4f8-4583-47ee-b9e6-95efb1fdd8ab</arg>
    <arg type="point">d2e5fff6-41d7-43b1-a75e-26fc1be1a07b</arg>
    <arg type="point">9d939cf3-bb8e-4de4-a687-f564ace6e9c8</arg>
    <arg type="point">9f36e510-7883-4cf4-8716-d2b6e705eb17</arg>
    <arg type="point">0c915a44-d801-43fd-96ab-40137d37871a</arg>
    <arg type="point">bc1f20d8-2196-4dff-87a6-d7088dce9d69</arg>
    <arg type="point">50c8bd8a-577f-4385-8223-97790a049a28</arg>
  </shape>
  <shape type="substroke" name="substroke" id="822b5906-193e-4105-8eef-8527ea01f9fb" time="1159077688796" x="1163" y="2306" color="-16777216" height="284" width="31" penTip="Ball" penWidth="10" penHeight="10" raster="CopyPen" start="0bfe11a0-9c55-4d75-8951-45878c1cb4eb" end="728a8aaf-101d-405d-bd30-adfcecee332f" source="ConverterJnt">
    <arg type="point">0bfe11a0-9c55-4d75-8951-45878c1cb4eb</arg>
    <arg type="point">3cb105e3-8ccb-41a2-893b-78005f24324a</arg>
    <arg type="point">115b005b-1f89-4ad4-9bae-a8d97acb65c2</arg>
    <arg type="point">ca86bfbe-dae5-4193-8422-923aac84d653</arg>
    <arg type="point">e22a6226-0cda-435a-b09e-b8d5cbb03b4c</arg>
    <arg type="point">b21e30bb-3659-4a88-a935-5beaa4830c7b</arg>
    <arg type="point">087b1a99-dab0-4138-85fe-e442e1212999</arg>
    <arg type="point">4cf44815-74bd-40ac-b56e-4b15e3c8bb48</arg>
    <arg type="point">3ab048e2-8185-4b41-98c6-ea3e2748c9ff</arg>
    <arg type="point">ef88bf6e-3708-4f2d-8211-1e44d0fbac04</arg>
    <arg type="point">8e3a442d-33e8-4bb3-bda1-025df6668b0f</arg>
    <arg type="point">783415c9-a7c8-4706-b3b6-1a5fb275e0dd</arg>
    <arg type="point">9d1e2411-8795-4e7a-a12d-2b74cffabac4</arg>
    <arg type="point">2af04767-db3b-4b16-a0c9-2af54648521c</arg>
    <arg type="point">5077f446-2c91-4545-8471-a1f5380bcacf</arg>
    <arg type="point">0286e1e4-624f-42b6-86c0-c5c1e33ad90b</arg>
    <arg type="point">397d2db4-cd85-4e1b-8af1-0a8da155b944</arg>
    <arg type="point">ea5a56df-7bd4-4b77-89f7-452ba0a866e8</arg>
    <arg type="point">d5856520-3c69-40b0-a768-3f8c241c2587</arg>
    <arg type="point">1b0fd933-4912-47a3-bae6-021399a5d62a</arg>
    <arg type="point">ea2021e4-d80d-4d6d-94f5-0f6dae3fec90</arg>
    <arg type="point">f6aae065-3a46-49b5-969a-573c845688c2</arg>
    <arg type="point">f34b7353-4ba7-4afd-bc18-8aaf42a2db15</arg>
    <arg type="point">685d93e3-b0ea-48b0-864d-aca25699d750</arg>
    <arg type="point">728a8aaf-101d-405d-bd30-adfcecee332f</arg>
  </shape>
  <shape type="substroke" name="substroke" id="74c78f46-3d60-4785-8f3a-79595f66ccbf" time="1159077689125" x="1157" y="2309" color="-16777216" height="122" width="191" penTip="Ball" penWidth="10" penHeight="10" raster="CopyPen" start="dc417fa7-24c6-4840-8a06-d3a8ee0b58be" end="60ea9a07-4e29-4ad4-a3e7-0b6b66f1bda2" source="ConverterJnt">
    <arg type="point">dc417fa7-24c6-4840-8a06-d3a8ee0b58be</arg>
    <arg type="point">ee858a9e-7244-45e5-a415-216123baa24a</arg>
    <arg type="point">b68c6729-ee03-4831-8151-66fd671c12f1</arg>
    <arg type="point">e3d4e053-0430-4237-aad7-f9ab6e12008d</arg>
    <arg type="point">b4b55fd7-7e62-45ce-89c1-836504e3f9ac</arg>
    <arg type="point">9ed982d9-b88d-4655-b618-6c5597df5a5c</arg>
    <arg type="point">a25a8e32-d14f-4a46-8bc8-cefb17f36cd8</arg>
    <arg type="point">5225d6fb-56b8-42af-8944-e8d80fcf3d67</arg>
    <arg type="point">69b0851c-1b5f-4fb7-b054-e4cffae9a001</arg>
    <arg type="point">9006b223-02af-40a9-bef7-2bc4c67a826d</arg>
    <arg type="point">993fa773-4494-4c92-b69e-44b9b4a9f8f5</arg>
    <arg type="point">45b5b92c-2da3-4318-bf37-70e8264fb62e</arg>
    <arg type="point">7ee4a99f-9e98-408a-8a4a-83172aa30ef6</arg>
    <arg type="point">739256c7-fd5c-459b-9f47-6b5044a3efe7</arg>
    <arg type="point">253270fe-4f23-4a9f-a462-098a7f5c6792</arg>
    <arg type="point">c9c777b6-cdb9-4c74-9444-9e66b66d4f4b</arg>
    <arg type="point">15eac86c-1cb0-4563-a2b5-10ab9d68a168</arg>
    <arg type="point">e06d8e41-b4b2-456b-99e6-79434f344339</arg>
    <arg type="point">de98c2ea-1ce3-402f-bc82-4356e8b92717</arg>
    <arg type="point">60ea9a07-4e29-4ad4-a3e7-0b6b66f1bda2</arg>
  </shape>
  <shape type="substroke" name="substroke" id="a992103d-dd81-48f3-9ead-4faf9612c1cf" time="1159077689305" x="1194" y="2440" color="-16777216" height="142" width="154" penTip="Ball" penWidth="10" penHeight="10" raster="CopyPen" start="80aa12bf-461d-4d78-8a0d-d0baca46daa5" end="bd5f6879-c368-4365-a128-a3a4600c1e55" source="ConverterJnt">
    <arg type="point">80aa12bf-461d-4d78-8a0d-d0baca46daa5</arg>
    <arg type="point">4d07472d-030b-47cb-a994-9af3054b99e1</arg>
    <arg type="point">c13e3fe2-54ec-45a2-95da-b51df8e2bc37</arg>
    <arg type="point">07894d9b-bd13-4d94-aa57-bbf6a71293b4</arg>
    <arg type="point">7f773466-d9b6-45a6-9dc6-6c889ef79129</arg>
    <arg type="point">c65bd5cf-f9ae-432d-8521-da5fa8025623</arg>
    <arg type="point">857162d7-5aba-483f-813f-e1f4e9c7d22f</arg>
    <arg type="point">ce93b200-ff4c-4713-877a-bebb0b916e8f</arg>
    <arg type="point">a8e28994-c218-4e18-8f26-c1b77bba444e</arg>
    <arg type="point">df6c0b76-8730-4780-a6d7-8fc9341cb806</arg>
    <arg type="point">b5d6d8e2-a29e-414e-b9a1-8a9f09cab310</arg>
    <arg type="point">d4c69997-62e9-4664-9327-c3696e2a2fd8</arg>
    <arg type="point">23429e2f-3ee0-4060-b98d-7ac04644a874</arg>
    <arg type="point">118ed935-d6b6-4ae4-927b-107e34d1de21</arg>
    <arg type="point">239260ab-1bf1-4045-b88b-335834e74268</arg>
    <arg type="point">805b0db3-cb07-48bb-a200-63ba8cd40f78</arg>
    <arg type="point">8a9f5598-fb04-4f5c-8b2a-345251a36d43</arg>
    <arg type="point">01e17911-7fed-420a-808f-c4e0da6a8730</arg>
    <arg type="point">83ff177f-7f73-45c9-91e7-fbcf7f456e6f</arg>
    <arg type="point">47861bea-a30e-4e60-8bd3-0d065469f833</arg>
    <arg type="point">7892c6e6-0c06-457e-9ce7-1e10bfe04e60</arg>
    <arg type="point">cd557fbc-9dff-4c16-a0c1-84addc4c4db5</arg>
    <arg type="point">ae5291b6-e1fe-44d8-84f0-3dbf8864e2c4</arg>
    <arg type="point">bd5f6879-c368-4365-a128-a3a4600c1e55</arg>
  </shape>
  <shape type="substroke" name="substroke" id="a35428ab-da47-4585-97cc-a7dea4f9212e" time="1159077689812" x="1381" y="2382" color="-16777216" height="107" width="158" penTip="Ball" penWidth="10" penHeight="10" raster="CopyPen" start="ebd7cd86-1242-440d-99ce-641f779ff2fb" end="65be1789-4618-4e75-bc95-a20354c08ffe" source="ConverterJnt">
    <arg type="point">ebd7cd86-1242-440d-99ce-641f779ff2fb</arg>
    <arg type="point">d09d71d2-498d-4c9e-b411-ee57a64558ed</arg>
    <arg type="point">8cab5fa6-0389-45ed-9835-f5a94632cf64</arg>
    <arg type="point">4ad82693-52aa-4964-bc04-bf3e8b9d1fa8</arg>
    <arg type="point">a741cced-f5f2-4542-9785-ab6cf5bb0637</arg>
    <arg type="point">5208b7fe-c868-4d9a-8097-c5ad6b33ec03</arg>
    <arg type="point">ee735eb3-b41a-4572-a6a5-feede83c0ae1</arg>
    <arg type="point">876f2869-4af6-462e-ae90-7868912e1eb7</arg>
    <arg type="point">09822aee-6d43-4cbe-be25-c8714278326a</arg>
    <arg type="point">1b8cc9c7-43f0-4071-962e-4501081df030</arg>
    <arg type="point">a1a2a187-67b6-49b8-a0db-73568cd59886</arg>
    <arg type="point">bbfa77d6-62a3-4203-a78b-570b94247e58</arg>
    <arg type="point">f7ffba9c-c87a-4f51-8d22-c76d381156da</arg>
    <arg type="point">892c164c-2a5a-4dbf-9275-41ebf77835d0</arg>
    <arg type="point">220e8dd2-08d4-4180-b338-4f38ca180dce</arg>
    <arg type="point">9e4d0b3e-60ba-4d88-905c-61972a764695</arg>
    <arg type="point">7530025e-1f8f-4380-a0fd-c52144500ab2</arg>
    <arg type="point">49f2012e-1884-4a63-b88b-486b1b111ccf</arg>
    <arg type="point">c36580eb-0487-48da-9080-9b8820002df2</arg>
    <arg type="point">20cedf2d-2062-499a-b698-ab45f9be4364</arg>
    <arg type="point">8541b8c8-a5f5-46a8-9a47-fab918ed0497</arg>
    <arg type="point">861b484a-b4f5-4d92-9419-a0022a73cbbf</arg>
    <arg type="point">5093ecac-2865-44fe-b797-a3239956049b</arg>
    <arg type="point">e5d18563-c6b7-49a0-92b1-513ac3fc1d3b</arg>
    <arg type="point">3d007996-b393-49b0-9e04-8bc4e9ad4fa3</arg>
    <arg type="point">a5d51877-551c-4fa6-b7dd-78793ff321f8</arg>
    <arg type="point">84c9bd56-601c-43a3-be41-38699fb3af9f</arg>
    <arg type="point">52bf3292-e6b9-4b2e-895a-f5db446c98cd</arg>
    <arg type="point">21d9066d-452d-42d9-93d6-e192ec837ad9</arg>
    <arg type="point">991ea037-e366-4bbd-8dc9-88b70d6f392d</arg>
    <arg type="point">9084f6be-53c7-4375-be87-1e1d68ccdc24</arg>
    <arg type="point">e9765217-41d9-4111-be1b-a78332940e4f</arg>
    <arg type="point">e6828dc9-9bf5-4456-a6cc-fa7373f48ad1</arg>
    <arg type="point">92fc3c59-f2dd-4fc3-914b-fa59202ab190</arg>
    <arg type="point">c7525e84-07b7-4579-b8a4-94478874d2b9</arg>
    <arg type="point">e3e49762-494e-4151-934b-86e844428fd1</arg>
    <arg type="point">5425b762-d5e5-490a-9f41-f57b7bb88756</arg>
    <arg type="point">edc2ecdf-1df9-47d9-b32c-cb27b5ee8d44</arg>
    <arg type="point">244c4cfa-0508-4a27-b621-48450ee2eab8</arg>
    <arg type="point">f26d107d-671a-423b-a2ab-2b5355840140</arg>
    <arg type="point">65be1789-4618-4e75-bc95-a20354c08ffe</arg>
  </shape>
  <shape type="substroke" name="substroke" id="9a935169-f2db-4079-9f49-3ddc7b783301" time="1159077729968" x="1549" y="1767" color="-16777216" height="679" width="914" penTip="Ball" penWidth="10" penHeight="10" raster="CopyPen" start="c3b265e1-3b0e-40e4-816a-f7978406ca2f" end="c9f7fd2e-a2bd-4b94-ada3-63453d806703" source="ConverterJnt">
    <arg type="point">c3b265e1-3b0e-40e4-816a-f7978406ca2f</arg>
    <arg type="point">7abd8006-dd6b-4682-b193-7b43d2de0b28</arg>
    <arg type="point">ddb236b1-85b4-4eff-ba9f-165c51b98f57</arg>
    <arg type="point">04afb804-fffb-41ca-8ff7-421237356396</arg>
    <arg type="point">fc8bb604-d879-4743-9eb4-826dbea37fa5</arg>
    <arg type="point">ea900bb7-2bd0-4a5c-8874-dc4de6c7a50f</arg>
    <arg type="point">388400ef-6c17-45d2-b025-f713b29aabd5</arg>
    <arg type="point">c1889ada-f2c0-457a-bfb9-58b0e6b23a89</arg>
    <arg type="point">ed0351d7-772e-49c0-ae16-128670f61cbf</arg>
    <arg type="point">8aff1936-f232-469c-9f5a-0f8299ab8e42</arg>
    <arg type="point">da49360e-e469-4d13-979f-c89578f9969f</arg>
    <arg type="point">3f34fea7-a405-48df-8780-20d51928b00f</arg>
    <arg type="point">757db3c2-cb0c-4b3e-8cd9-4afba3239cd6</arg>
    <arg type="point">0879b83e-8098-413f-bbc0-7ac301e2c432</arg>
    <arg type="point">533a4f0b-cfdc-4ec4-9798-8779cf2f0357</arg>
    <arg type="point">ea2bced0-0dd1-4268-b821-c08201a9a365</arg>
    <arg type="point">50778b09-5991-42bf-8d73-fdc9c768fb2c</arg>
    <arg type="point">a0c77fa0-c827-4294-bda4-60b90c582378</arg>
    <arg type="point">0665b773-0d24-49ca-befa-4e49152e81f5</arg>
    <arg type="point">42527744-e527-427a-9945-62640f07560a</arg>
    <arg type="point">aa4aa014-23e2-4a10-b506-b04ce3b3e2d1</arg>
    <arg type="point">d0d7303f-0a9c-4094-9d2c-8a0fd83f3050</arg>
    <arg type="point">8f04be38-4eff-4316-bd7e-7882716cee8b</arg>
    <arg type="point">af298423-1935-4284-9c7f-ca1284767cd8</arg>
    <arg type="point">7c847f39-e505-4d54-b468-de5c138d4e8b</arg>
    <arg type="point">eb032651-25f5-44fb-ae7f-be9ba1cc8841</arg>
    <arg type="point">424f699e-7348-4889-b31c-87f16696d1e4</arg>
    <arg type="point">8239dace-c0fd-4e4e-a95e-43af38c2566f</arg>
    <arg type="point">5793130b-b58b-4009-a049-28aef309a681</arg>
    <arg type="point">68137477-52a7-4f94-b711-5ed35042314e</arg>
    <arg type="point">f051ab61-da84-478f-aaa2-c529bdf75fa1</arg>
    <arg type="point">1b372e5c-88a3-492a-b552-23962300ecd0</arg>
    <arg type="point">fad7cba8-dfcc-497f-b2e7-95b85ba48a3c</arg>
    <arg type="point">17852771-29d7-4c66-b463-9399ce2cbeb8</arg>
    <arg type="point">966fb974-71af-40c4-bb04-eb957c5549a4</arg>
    <arg type="point">44924b11-7d4c-456b-a4d0-1c0cb05261f8</arg>
    <arg type="point">c9cd9ab5-bcec-4a5a-8c2f-b593087a5b0f</arg>
    <arg type="point">c43b9656-5c50-4f97-9510-97fcb79396f1</arg>
    <arg type="point">2dc65c6e-e1ba-447c-a8cd-4211c8bcd99c</arg>
    <arg type="point">9003fec7-6a59-489f-8dca-ffff5d9040b6</arg>
    <arg type="point">3053208f-1880-4140-81a1-d2e6aae2726d</arg>
  </shape>
  <shape type="stroke" name="stroke" id="5ac170b9-5f7b-4adb-a890-023f8efb890e" time="1159077688453" x="951" y="2069" height="385" width="219" start="ad4753b6-5d94-4729-aea0-5218db55c355" end="ad4753b6-5d94-4729-aea0-5218db55c355">
    <arg type="substroke">ad4753b6-5d94-4729-aea0-5218db55c355</arg>
  </shape>
  <shape type="stroke" name="stroke" id="bfce8ed9-e08a-4682-a7df-a7dbb87ed3e9" time="1159077688796" x="1163" y="2306" height="284" width="31" start="822b5906-193e-4105-8eef-8527ea01f9fb" end="822b5906-193e-4105-8eef-8527ea01f9fb">
    <arg type="substroke">822b5906-193e-4105-8eef-8527ea01f9fb</arg>
  </shape>
  <shape type="stroke" name="stroke" id="6e19b9ce-8f8c-4e1a-86d8-eca2d61d773e" time="1159077689125" x="1157" y="2309" height="122" width="191" start="74c78f46-3d60-4785-8f3a-79595f66ccbf" end="74c78f46-3d60-4785-8f3a-79595f66ccbf">
    <arg type="substroke">74c78f46-3d60-4785-8f3a-79595f66ccbf</arg>
  </shape>
  <shape type="stroke" name="stroke" id="52e6affd-29de-4b95-bd65-c482a7d2ad48" time="1159077689305" x="1194" y="2440" height="142" width="154" start="a992103d-dd81-48f3-9ead-4faf9612c1cf" end="a992103d-dd81-48f3-9ead-4faf9612c1cf">
    <arg type="substroke">a992103d-dd81-48f3-9ead-4faf9612c1cf</arg>
  </shape>
  <shape type="stroke" name="stroke" id="d9163701-f8e8-4212-acc8-5d4f88bfc22f" time="1159077689812" x="1381" y="2382" height="107" width="158" start="a35428ab-da47-4585-97cc-a7dea4f9212e" end="a35428ab-da47-4585-97cc-a7dea4f9212e">
    <arg type="substroke">a35428ab-da47-4585-97cc-a7dea4f9212e</arg>
  </shape>
  <shape type="stroke" name="stroke" id="4c1b2f87-bea7-4910-b55f-8c28f5815b5a" time="1159077729968" x="1549" y="1767" height="679" width="914" start="9a935169-f2db-4079-9f49-3ddc7b783301" end="9a935169-f2db-4079-9f49-3ddc7b783301">
    <arg type="substroke">9a935169-f2db-4079-9f49-3ddc7b783301</arg>
  </shape>
</sketch>