<?xml version="1.0" encoding="utf-8"?>
<sketch id="4cf79bf9-ebf7-4d82-aeff-c564acf0360b">
  <point x="1292" y="1376" pressure="127" time="1157999588718" name="point" id="8aed53ff-08b9-4c37-86f4-d21b50ded1a9" />
  <point x="1292" y="1376" pressure="127" time="1157999588725" name="point" id="8c8454cb-b815-4a7e-b791-94c3c0594e79" />
  <point x="1293" y="1383" pressure="127" time="1157999588733" name="point" id="67e41158-38b8-43da-901e-23cd4bcc5854" />
  <point x="1296" y="1394" pressure="127" time="1157999588740" name="point" id="d55d7f42-888a-40ab-8b01-cc3512ec88dc" />
  <point x="1299" y="1409" pressure="127" time="1157999588748" name="point" id="78571953-703a-4101-8a6a-c2b094f75567" />
  <point x="1305" y="1426" pressure="127" time="1157999588755" name="point" id="335af2c1-c9a0-4653-b8b1-f8d40277f319" />
  <point x="1309" y="1449" pressure="127" time="1157999588763" name="point" id="3805ed19-12a9-45f8-86f0-35b6acee55ec" />
  <point x="1315" y="1475" pressure="127" time="1157999588770" name="point" id="f75d7433-9049-43aa-b520-039e331cbf0a" />
  <point x="1322" y="1505" pressure="127" time="1157999588778" name="point" id="638c3e3d-ee23-4bab-9ec4-1f5c87d6f3ea" />
  <point x="1328" y="1535" pressure="127" time="1157999588785" name="point" id="db23406d-8eb4-4466-b366-9d8eb8f4853a" />
  <point x="1333" y="1567" pressure="127" time="1157999588793" name="point" id="0ff018f8-f229-4597-a088-907e4dc8df24" />
  <point x="1338" y="1598" pressure="127" time="1157999588800" name="point" id="45669e53-0478-4a39-8f1a-3a28bf4f8b0d" />
  <point x="1342" y="1627" pressure="127" time="1157999588808" name="point" id="7c21a2e7-4b68-4d29-8d1d-80c166e7be10" />
  <point x="1346" y="1653" pressure="127" time="1157999588815" name="point" id="d96f27c0-b0f2-49b5-9524-9311471520ad" />
  <point x="1349" y="1672" pressure="127" time="1157999588823" name="point" id="4e7ab582-e868-44ea-8a5f-a5e9d51d0ab2" />
  <point x="1351" y="1687" pressure="127" time="1157999588830" name="point" id="bf5ddc65-c33f-4226-bdb7-7b6f25cc8d75" />
  <point x="1352" y="1697" pressure="127" time="1157999588838" name="point" id="37907c52-efd6-43f8-afb1-27f92e5545af" />
  <point x="1349" y="1702" pressure="127" time="1157999588845" name="point" id="a43790f1-edff-41d1-8f8c-337324b2bed9" />
  <point x="1349" y="1702" pressure="127" time="1157999588853" name="point" id="2abd529c-0bf2-492a-b729-2594ed2cf402" />
  <point x="1344" y="1697" pressure="127" time="1157999588860" name="point" id="716e9756-f647-4762-a893-583bffaced14" />
  <point x="1340" y="1692" pressure="127" time="1157999588868" name="point" id="669849cd-ef8b-484a-99d9-ee46178fc883" />
  <point x="1336" y="1685" pressure="127" time="1157999588875" name="point" id="0c3195c0-bc74-45c1-bb69-f0d677ad348c" />
  <point x="1331" y="1679" pressure="127" time="1157999588883" name="point" id="a018ed7d-5b9d-4de4-b9cf-78395187a147" />
  <point x="1295" y="1355" pressure="127" time="1157999589250" name="point" id="09bf3e8f-b1ac-444c-b570-084e8fa2830d" />
  <point x="1295" y="1355" pressure="127" time="1157999589257" name="point" id="76f9a670-afe2-48b4-a749-0ea2b95c4802" />
  <point x="1295" y="1355" pressure="127" time="1157999589265" name="point" id="9022cb24-730b-4b36-9aa9-1f57c1a4aff4" />
  <point x="1295" y="1355" pressure="127" time="1157999589272" name="point" id="8e9bf461-dbdb-4cc5-9689-f31c89f91438" />
  <point x="1295" y="1355" pressure="127" time="1157999589280" name="point" id="6953fc15-1ab1-4436-b83a-fff449af0377" />
  <point x="1295" y="1355" pressure="127" time="1157999589287" name="point" id="925f41ca-e8b9-4c9b-84c6-dae1928026f2" />
  <point x="1295" y="1355" pressure="127" time="1157999589295" name="point" id="2d98087d-8a83-4b69-9e90-c2266f329d73" />
  <point x="1298" y="1349" pressure="127" time="1157999589302" name="point" id="78b212f4-99e0-4ab9-a119-10cb599c5951" />
  <point x="1298" y="1349" pressure="127" time="1157999589310" name="point" id="cdb26a01-3dcd-417f-b1b6-ff6ca7da5658" />
  <point x="1305" y="1346" pressure="127" time="1157999589317" name="point" id="7ea423c0-0387-4d86-8744-7fbe4372a108" />
  <point x="1310" y="1344" pressure="127" time="1157999589325" name="point" id="66aefff6-18f5-4c77-b5f8-3766ae839694" />
  <point x="1317" y="1342" pressure="127" time="1157999589332" name="point" id="44093235-0f2e-4990-a57a-7d62c80ee0cb" />
  <point x="1325" y="1342" pressure="127" time="1157999589340" name="point" id="f380aeea-1a19-47e0-b770-b465db03e1c0" />
  <point x="1334" y="1340" pressure="127" time="1157999589347" name="point" id="cdae2f71-65b2-44f7-8516-e214340ecbe7" />
  <point x="1344" y="1340" pressure="127" time="1157999589355" name="point" id="78380827-2459-4f0c-8f82-801799c6c54f" />
  <point x="1355" y="1340" pressure="127" time="1157999589362" name="point" id="3f6a20ae-7a65-429f-952e-daaa18838759" />
  <point x="1366" y="1340" pressure="127" time="1157999589370" name="point" id="94624271-485c-4f7d-8bf3-93312956a6bd" />
  <point x="1379" y="1340" pressure="127" time="1157999589377" name="point" id="80bff8da-2b26-42b7-ad90-c9d96cfc08ec" />
  <point x="1392" y="1341" pressure="127" time="1157999589385" name="point" id="ae22cf91-c4fe-4020-babb-72dffc5ecabe" />
  <point x="1406" y="1341" pressure="127" time="1157999589392" name="point" id="44fa0c3e-a382-47ee-964f-cc0c271f4365" />
  <point x="1419" y="1343" pressure="127" time="1157999589400" name="point" id="c3b65041-69f3-42ea-8f59-4b1202814027" />
  <point x="1435" y="1344" pressure="127" time="1157999589407" name="point" id="4ff1f00d-1603-46a8-b0fe-8d281a66e568" />
  <point x="1451" y="1346" pressure="127" time="1157999589415" name="point" id="109cbcd4-edec-4a7a-8f19-18fb88d6ba13" />
  <point x="1467" y="1349" pressure="127" time="1157999589422" name="point" id="834b8197-1cad-48c3-baa9-2e18b1c0719c" />
  <point x="1483" y="1353" pressure="127" time="1157999589430" name="point" id="6d2042d3-ab64-49b6-a7d9-69c65d960f91" />
  <point x="1501" y="1357" pressure="127" time="1157999589437" name="point" id="6dc04969-588a-47ae-8deb-9ecda9234220" />
  <point x="1519" y="1361" pressure="127" time="1157999589445" name="point" id="aee70502-70ba-4ac2-8f37-d704e3c8ded0" />
  <point x="1536" y="1368" pressure="127" time="1157999589453" name="point" id="a722b072-af5b-41a4-8094-b8fd271a2f78" />
  <point x="1553" y="1375" pressure="127" time="1157999589460" name="point" id="1d1ee33d-de42-48ff-92fd-9c615cf7bfe6" />
  <point x="1570" y="1384" pressure="127" time="1157999589468" name="point" id="015999a1-e8d7-4758-b7fc-1aa5f473d9ca" />
  <point x="1586" y="1393" pressure="127" time="1157999589475" name="point" id="25aa6e77-ebf0-4c97-b671-213846156110" />
  <point x="1601" y="1405" pressure="127" time="1157999589483" name="point" id="1ce3bc91-b48f-4204-9b52-cff46fc3a2b2" />
  <point x="1614" y="1420" pressure="127" time="1157999589490" name="point" id="9831758c-8c5f-4a9d-83af-15adf7080b22" />
  <point x="1624" y="1435" pressure="127" time="1157999589498" name="point" id="9b26edec-0b12-48aa-9dbe-7fdc8f8bafb9" />
  <point x="1631" y="1455" pressure="127" time="1157999589505" name="point" id="706a77c7-5e48-4cd7-bb60-6df78a45957b" />
  <point x="1635" y="1475" pressure="127" time="1157999589513" name="point" id="80bd7a5a-6b53-4fd2-8376-2184ae7aaec5" />
  <point x="1636" y="1499" pressure="127" time="1157999589520" name="point" id="cc5cc295-db11-40b2-82a5-141f4864fea1" />
  <point x="1631" y="1524" pressure="127" time="1157999589528" name="point" id="bc53a9ee-154a-4e63-8723-59347d837c5e" />
  <point x="1620" y="1548" pressure="127" time="1157999589535" name="point" id="33198a96-c603-4866-b164-a51f0a03c4c9" />
  <point x="1605" y="1571" pressure="127" time="1157999589543" name="point" id="27278fca-9135-4153-a0d8-f464fd5d3a73" />
  <point x="1588" y="1591" pressure="127" time="1157999589550" name="point" id="0a5b6a88-cfad-4e21-94cd-c8e11b1b94ad" />
  <point x="1567" y="1612" pressure="127" time="1157999589558" name="point" id="5f83ca16-1a22-4989-95ff-9e240cd622bb" />
  <point x="1543" y="1629" pressure="127" time="1157999589565" name="point" id="25af4a45-1446-4bd7-9f39-0236baa26e8b" />
  <point x="1516" y="1642" pressure="127" time="1157999589573" name="point" id="a5aea905-4277-455b-bb40-b5a626146ee8" />
  <point x="1491" y="1654" pressure="127" time="1157999589580" name="point" id="85fbe7d7-6892-4371-b9c3-9694a9cf16d3" />
  <point x="1467" y="1663" pressure="127" time="1157999589588" name="point" id="6188d379-d1e7-4580-9917-c0028f69ebcf" />
  <point x="1447" y="1669" pressure="127" time="1157999589595" name="point" id="e5f7aa72-1b08-4946-a815-9aed7854b7b8" />
  <point x="1426" y="1677" pressure="127" time="1157999589603" name="point" id="91b1f8c1-03af-4881-ad80-767238f677e6" />
  <point x="1409" y="1681" pressure="127" time="1157999589610" name="point" id="9963a49a-01f5-43ab-8a4c-0a4d94f16d90" />
  <point x="1395" y="1687" pressure="127" time="1157999589618" name="point" id="19a41d9e-734e-4341-81cd-8e1f70851b43" />
  <point x="1385" y="1690" pressure="127" time="1157999589625" name="point" id="64dfc064-ecd2-447f-adbd-9abfcd5084ad" />
  <point x="1379" y="1694" pressure="127" time="1157999589633" name="point" id="e3f0741c-2aa2-4d53-84ba-543bc629a377" />
  <shape type="substroke" name="substroke" id="5535c6e5-232f-434d-bc26-50aee284a759" time="1157999588890" x="1292" y="1376" color="-65536" height="326" width="60" penTip="Ball" penWidth="30" penHeight="30" raster="CopyPen" start="8aed53ff-08b9-4c37-86f4-d21b50ded1a9" end="a018ed7d-5b9d-4de4-b9cf-78395187a147" source="ConverterJnt">
    <arg type="point">8aed53ff-08b9-4c37-86f4-d21b50ded1a9</arg>
    <arg type="point">8c8454cb-b815-4a7e-b791-94c3c0594e79</arg>
    <arg type="point">67e41158-38b8-43da-901e-23cd4bcc5854</arg>
    <arg type="point">d55d7f42-888a-40ab-8b01-cc3512ec88dc</arg>
    <arg type="point">78571953-703a-4101-8a6a-c2b094f75567</arg>
    <arg type="point">335af2c1-c9a0-4653-b8b1-f8d40277f319</arg>
    <arg type="point">3805ed19-12a9-45f8-86f0-35b6acee55ec</arg>
    <arg type="point">f75d7433-9049-43aa-b520-039e331cbf0a</arg>
    <arg type="point">638c3e3d-ee23-4bab-9ec4-1f5c87d6f3ea</arg>
    <arg type="point">db23406d-8eb4-4466-b366-9d8eb8f4853a</arg>
    <arg type="point">0ff018f8-f229-4597-a088-907e4dc8df24</arg>
    <arg type="point">45669e53-0478-4a39-8f1a-3a28bf4f8b0d</arg>
    <arg type="point">7c21a2e7-4b68-4d29-8d1d-80c166e7be10</arg>
    <arg type="point">d96f27c0-b0f2-49b5-9524-9311471520ad</arg>
    <arg type="point">4e7ab582-e868-44ea-8a5f-a5e9d51d0ab2</arg>
    <arg type="point">bf5ddc65-c33f-4226-bdb7-7b6f25cc8d75</arg>
    <arg type="point">37907c52-efd6-43f8-afb1-27f92e5545af</arg>
    <arg type="point">a43790f1-edff-41d1-8f8c-337324b2bed9</arg>
    <arg type="point">2abd529c-0bf2-492a-b729-2594ed2cf402</arg>
    <arg type="point">716e9756-f647-4762-a893-583bffaced14</arg>
    <arg type="point">669849cd-ef8b-484a-99d9-ee46178fc883</arg>
    <arg type="point">0c3195c0-bc74-45c1-bb69-f0d677ad348c</arg>
    <arg type="point">a018ed7d-5b9d-4de4-b9cf-78395187a147</arg>
  </shape>
  <shape type="substroke" name="substroke" id="986a4aa5-3e9b-41f7-a8d7-12e1110d20a7" time="1157999589640" x="1295" y="1340" color="-65536" height="354" width="341" penTip="Ball" penWidth="30" penHeight="30" raster="CopyPen" start="09bf3e8f-b1ac-444c-b570-084e8fa2830d" end="e3f0741c-2aa2-4d53-84ba-543bc629a377" source="ConverterJnt">
    <arg type="point">09bf3e8f-b1ac-444c-b570-084e8fa2830d</arg>
    <arg type="point">76f9a670-afe2-48b4-a749-0ea2b95c4802</arg>
    <arg type="point">9022cb24-730b-4b36-9aa9-1f57c1a4aff4</arg>
    <arg type="point">8e9bf461-dbdb-4cc5-9689-f31c89f91438</arg>
    <arg type="point">6953fc15-1ab1-4436-b83a-fff449af0377</arg>
    <arg type="point">925f41ca-e8b9-4c9b-84c6-dae1928026f2</arg>
    <arg type="point">2d98087d-8a83-4b69-9e90-c2266f329d73</arg>
    <arg type="point">78b212f4-99e0-4ab9-a119-10cb599c5951</arg>
    <arg type="point">cdb26a01-3dcd-417f-b1b6-ff6ca7da5658</arg>
    <arg type="point">7ea423c0-0387-4d86-8744-7fbe4372a108</arg>
    <arg type="point">66aefff6-18f5-4c77-b5f8-3766ae839694</arg>
    <arg type="point">44093235-0f2e-4990-a57a-7d62c80ee0cb</arg>
    <arg type="point">f380aeea-1a19-47e0-b770-b465db03e1c0</arg>
    <arg type="point">cdae2f71-65b2-44f7-8516-e214340ecbe7</arg>
    <arg type="point">78380827-2459-4f0c-8f82-801799c6c54f</arg>
    <arg type="point">3f6a20ae-7a65-429f-952e-daaa18838759</arg>
    <arg type="point">94624271-485c-4f7d-8bf3-93312956a6bd</arg>
    <arg type="point">80bff8da-2b26-42b7-ad90-c9d96cfc08ec</arg>
    <arg type="point">ae22cf91-c4fe-4020-babb-72dffc5ecabe</arg>
    <arg type="point">44fa0c3e-a382-47ee-964f-cc0c271f4365</arg>
    <arg type="point">c3b65041-69f3-42ea-8f59-4b1202814027</arg>
    <arg type="point">4ff1f00d-1603-46a8-b0fe-8d281a66e568</arg>
    <arg type="point">109cbcd4-edec-4a7a-8f19-18fb88d6ba13</arg>
    <arg type="point">834b8197-1cad-48c3-baa9-2e18b1c0719c</arg>
    <arg type="point">6d2042d3-ab64-49b6-a7d9-69c65d960f91</arg>
    <arg type="point">6dc04969-588a-47ae-8deb-9ecda9234220</arg>
    <arg type="point">aee70502-70ba-4ac2-8f37-d704e3c8ded0</arg>
    <arg type="point">a722b072-af5b-41a4-8094-b8fd271a2f78</arg>
    <arg type="point">1d1ee33d-de42-48ff-92fd-9c615cf7bfe6</arg>
    <arg type="point">015999a1-e8d7-4758-b7fc-1aa5f473d9ca</arg>
    <arg type="point">25aa6e77-ebf0-4c97-b671-213846156110</arg>
    <arg type="point">1ce3bc91-b48f-4204-9b52-cff46fc3a2b2</arg>
    <arg type="point">9831758c-8c5f-4a9d-83af-15adf7080b22</arg>
    <arg type="point">9b26edec-0b12-48aa-9dbe-7fdc8f8bafb9</arg>
    <arg type="point">706a77c7-5e48-4cd7-bb60-6df78a45957b</arg>
    <arg type="point">80bd7a5a-6b53-4fd2-8376-2184ae7aaec5</arg>
    <arg type="point">cc5cc295-db11-40b2-82a5-141f4864fea1</arg>
    <arg type="point">bc53a9ee-154a-4e63-8723-59347d837c5e</arg>
    <arg type="point">33198a96-c603-4866-b164-a51f0a03c4c9</arg>
    <arg type="point">27278fca-9135-4153-a0d8-f464fd5d3a73</arg>
    <arg type="point">0a5b6a88-cfad-4e21-94cd-c8e11b1b94ad</arg>
    <arg type="point">5f83ca16-1a22-4989-95ff-9e240cd622bb</arg>
    <arg type="point">25af4a45-1446-4bd7-9f39-0236baa26e8b</arg>
    <arg type="point">a5aea905-4277-455b-bb40-b5a626146ee8</arg>
    <arg type="point">85fbe7d7-6892-4371-b9c3-9694a9cf16d3</arg>
    <arg type="point">6188d379-d1e7-4580-9917-c0028f69ebcf</arg>
    <arg type="point">e5f7aa72-1b08-4946-a815-9aed7854b7b8</arg>
    <arg type="point">91b1f8c1-03af-4881-ad80-767238f677e6</arg>
    <arg type="point">9963a49a-01f5-43ab-8a4c-0a4d94f16d90</arg>
    <arg type="point">19a41d9e-734e-4341-81cd-8e1f70851b43</arg>
    <arg type="point">64dfc064-ecd2-447f-adbd-9abfcd5084ad</arg>
    <arg type="point">e3f0741c-2aa2-4d53-84ba-543bc629a377</arg>
  </shape>
  <shape type="stroke" name="stroke" id="10975dd8-a74c-4a97-9a6c-e6179add650c" time="1157999588890" x="1292" y="1376" height="326" width="60" start="5535c6e5-232f-434d-bc26-50aee284a759" end="5535c6e5-232f-434d-bc26-50aee284a759">
    <arg type="substroke">5535c6e5-232f-434d-bc26-50aee284a759</arg>
  </shape>
  <shape type="stroke" name="stroke" id="0d77450c-96f5-4c9c-b9a8-8b9765b1b80c" time="1157999589640" x="1295" y="1340" height="354" width="341" start="986a4aa5-3e9b-41f7-a8d7-12e1110d20a7" end="986a4aa5-3e9b-41f7-a8d7-12e1110d20a7">
    <arg type="substroke">986a4aa5-3e9b-41f7-a8d7-12e1110d20a7</arg>
  </shape>
</sketch>